indico_themes_legacy/__init__.py
indico_themes_legacy/plugin.py
indico_themes_legacy/themes-legacy.yaml
indico_themes_legacy/static/dist/manifest.json
indico_themes_legacy/static/dist/css/themes_nicecompact.d2b4b1d5.css
indico_themes_legacy/static/dist/css/themes_nicecompact.d2b4b1d5.css.map
indico_themes_legacy/static/dist/js/monaco.css.worker.js
indico_themes_legacy/static/dist/js/monaco.css.worker.js.map
indico_themes_legacy/static/dist/js/monaco.editor.worker.js
indico_themes_legacy/static/dist/js/monaco.editor.worker.js.map
indico_themes_legacy/static/dist/js/monaco.html.worker.js
indico_themes_legacy/static/dist/js/monaco.html.worker.js.map
indico_themes_legacy/static/dist/js/themes_nicecompact.282072c0.bundle.js
indico_themes_legacy/templates/compact_event.html
indico_themes_legacy/templates/compact_timetable.html
indico_themes_legacy/themes/compact.scss
indico_themes_legacy/translations/messages.pot
indico_themes_legacy/translations/cs_CZ/LC_MESSAGES/messages.mo
indico_themes_legacy/translations/cs_CZ/LC_MESSAGES/messages.po
indico_themes_legacy/translations/de_DE/LC_MESSAGES/messages.mo
indico_themes_legacy/translations/de_DE/LC_MESSAGES/messages.po
indico_themes_legacy/translations/en_CA/LC_MESSAGES/messages.mo
indico_themes_legacy/translations/en_CA/LC_MESSAGES/messages.po
indico_themes_legacy/translations/en_GB/LC_MESSAGES/messages.mo
indico_themes_legacy/translations/en_GB/LC_MESSAGES/messages.po
indico_themes_legacy/translations/es_ES/LC_MESSAGES/messages.mo
indico_themes_legacy/translations/es_ES/LC_MESSAGES/messages.po
indico_themes_legacy/translations/fr_FR/LC_MESSAGES/messages.mo
indico_themes_legacy/translations/fr_FR/LC_MESSAGES/messages.po
indico_themes_legacy/translations/hu_HU/LC_MESSAGES/messages.mo
indico_themes_legacy/translations/hu_HU/LC_MESSAGES/messages.po
indico_themes_legacy/translations/it_IT/LC_MESSAGES/messages.mo
indico_themes_legacy/translations/it_IT/LC_MESSAGES/messages.po
indico_plugin_themes_legacy-3.3.2.dist-info/METADATA
indico_plugin_themes_legacy-3.3.2.dist-info/WHEEL
indico_plugin_themes_legacy-3.3.2.dist-info/entry_points.txt
indico_plugin_themes_legacy-3.3.2.dist-info/RECORD
